odoo10_addon_sale_invoice_policy-10.0.1.0.1-py3.8-nspkg.pth
odoo/addons/sale_invoice_policy/README.rst
odoo/addons/sale_invoice_policy/__init__.py
odoo/addons/sale_invoice_policy/__manifest__.py
odoo/addons/sale_invoice_policy/post_init_hook.py
odoo/addons/sale_invoice_policy/i18n/ca.po
odoo/addons/sale_invoice_policy/i18n/es.po
odoo/addons/sale_invoice_policy/i18n/fr.po
odoo/addons/sale_invoice_policy/i18n/sale_invoice_policy.pot
odoo/addons/sale_invoice_policy/models/__init__.py
odoo/addons/sale_invoice_policy/models/product_template.py
odoo/addons/sale_invoice_policy/models/sale_order.py
odoo/addons/sale_invoice_policy/models/sale_order_line.py
odoo/addons/sale_invoice_policy/static/description/icon.png
odoo/addons/sale_invoice_policy/tests/__init__.py
odoo/addons/sale_invoice_policy/tests/test_sale_invoice_policy.py
odoo/addons/sale_invoice_policy/views/product_template_view.xml
odoo/addons/sale_invoice_policy/views/sale_view.xml
odoo/addons/sale_invoice_policy/wizards/__init__.py
odoo/addons/sale_invoice_policy/wizards/res_config.py
odoo/addons/sale_invoice_policy/wizards/res_config_view.xml
odoo10_addon_sale_invoice_policy-10.0.1.0.1.dist-info/METADATA
odoo10_addon_sale_invoice_policy-10.0.1.0.1.dist-info/WHEEL
odoo10_addon_sale_invoice_policy-10.0.1.0.1.dist-info/namespace_packages.txt
odoo10_addon_sale_invoice_policy-10.0.1.0.1.dist-info/top_level.txt
odoo10_addon_sale_invoice_policy-10.0.1.0.1.dist-info/RECORD
